wows_api_async/__init__.py
wows_api_async/cache/__init__.py
wows_api_async/cache/base.py
wows_api_async/cache/file.py
wows_api_async/cache/redis.py
wows_api_async/cache/tools.py
wows_api_async/fetcher.py
wows_api_async/nodes/__init__.py
wows_api_async/nodes/account.py
wows_api_async/nodes/clans.py
wows_api_async/nodes/encyclopedia.py
wows_api_async/nodes/models.py
wows_api_async/nodes/ships.py
wows_api_async/root.py
wows_api_async/sub_node.py
wows_api_async/tools.py
wows_api_async-0.1.2.dist-info/WHEEL
wows_api_async-0.1.2.dist-info/METADATA
wows_api_async-0.1.2.dist-info/RECORD
