Metadata-Version: 2.1
Name: wows-api-async
Version: 0.1.2
Summary: async python api for world of warships
Home-page: https://github.com/voidpp/wows-api-async
License: MIT
Author: Lajos Santa
Author-email: santa.lajos@gmail.com
Requires-Python: >=3.9,<4.0
Classifier: License :: OSI Approved :: MIT License
Classifier: Programming Language :: Python :: 3
Classifier: Programming Language :: Python :: 3.9
Requires-Dist: aioredis (>=1.3.1,<2.0.0)
Requires-Dist: httpx (>=0.16.1,<0.17.0)
Requires-Dist: pydantic (>=1.7.3,<2.0.0)
Project-URL: Repository, https://github.com/voidpp/wows-api-async
